[
    { "vendorName": "IBM", "modelName": "3033:s", "MYCT": 57, "MMIN": 4000, "MMAX": 16000, "CACH": 1, "CHMIN": 6, "CHMAX": 12, "PRP": 132, "ERP": 82 },
    { "vendorName": "IBM", "modelName": "3033:u", "MYCT": 57, "MMIN": 4000, "MMAX": 24000, "CACH": 64, "CHMIN": 12, "CHMAX": 16, "PRP": 237, "ERP": 171 },
    { "vendorName": "IBM", "modelName": "3081", "MYCT": 26, "MMIN": 16000, "MMAX": 32000, "CACH": 64, "CHMIN": 16, "CHMAX": 24, "PRP": 465, "ERP": 361 },
    { "vendorName": "IBM", "modelName": "3081:d", "MYCT": 26, "MMIN": 16000, "MMAX": 32000, "CACH": 64, "CHMIN": 8, "CHMAX": 24, "PRP": 465, "ERP": 350 },
    { "vendorName": "IBM", "modelName": "3083:b", "MYCT": 26, "MMIN": 8000, "MMAX": 32000, "CACH": 0, "CHMIN": 8, "CHMAX": 24, "PRP": 277, "ERP": 220 },
    { "vendorName": "IBM", "modelName": "3083:e", "MYCT": 26, "MMIN": 8000, "MMAX": 16000, "CACH": 0, "CHMIN": 8, "CHMAX": 16, "PRP": 185, "ERP": 113 },
    { "vendorName": "IBM", "modelName": "370/125-2", "MYCT": 480, "MMIN": 96, "MMAX": 512, "CACH": 0, "CHMIN": 1, "CHMAX": 1, "PRP": 6, "ERP": 15 },
    { "vendorName": "IBM", "modelName": "370/148", "MYCT": 203, "MMIN": 1000, "MMAX": 2000, "CACH": 0, "CHMIN": 1, "CHMAX": 5, "PRP": 24, "ERP": 21 },
    { "vendorName": "IBM", "modelName": "370/158-3", "MYCT": 115, "MMIN": 512, "MMAX": 6000, "CACH": 16, "CHMIN": 1, "CHMAX": 6, "PRP": 45, "ERP": 35 },
    { "vendorName": "IBM", "modelName": "38/3", "MYCT": 1100, "MMIN": 512, "MMAX": 1500, "CACH": 0, "CHMIN": 1, "CHMAX": 1, "PRP": 7, "ERP": 18 },
    { "vendorName": "IBM", "modelName": "38/4", "MYCT": 1100, "MMIN": 768, "MMAX": 2000, "CACH": 0, "CHMIN": 1, "CHMAX": 1, "PRP": 13, "ERP": 20 },
    { "vendorName": "IBM", "modelName": "38/5", "MYCT": 600, "MMIN": 768, "MMAX": 2000, "CACH": 0, "CHMIN": 1, "CHMAX": 1, "PRP": 16, "ERP": 20 },
    { "vendorName": "IBM", "modelName": "38/7", "MYCT": 400, "MMIN": 2000, "MMAX": 4000, "CACH": 0, "CHMIN": 1, "CHMAX": 1, "PRP": 32, "ERP": 28 },
    { "vendorName": "IBM", "modelName": "38/8", "MYCT": 400, "MMIN": 4000, "MMAX": 8000, "CACH": 0, "CHMIN": 1, "CHMAX": 1, "PRP": 32, "ERP": 45 },
    { "vendorName": "IBM", "modelName": "4321", "MYCT": 900, "MMIN": 1000, "MMAX": 1000, "CACH": 0, "CHMIN": 1, "CHMAX": 2, "PRP": 11, "ERP": 18 },
    { "vendorName": "IBM", "modelName": "4331-1", "MYCT": 900, "MMIN": 512, "MMAX": 1000, "CACH": 0, "CHMIN": 1, "CHMAX": 2, "PRP": 11, "ERP": 17 },
    { "vendorName": "IBM", "modelName": "4331-11", "MYCT": 900, "MMIN": 1000, "MMAX": 4000, "CACH": 4, "CHMIN": 1, "CHMAX": 2, "PRP": 18, "ERP": 26 },
    { "vendorName": "IBM", "modelName": "4331-2", "MYCT": 900, "MMIN": 1000, "MMAX": 4000, "CACH": 8, "CHMIN": 1, "CHMAX": 2, "PRP": 22, "ERP": 28 },
    { "vendorName": "IBM", "modelName": "4341", "MYCT": 900, "MMIN": 2000, "MMAX": 4000, "CACH": 0, "CHMIN": 3, "CHMAX": 6, "PRP": 37, "ERP": 28 },
    { "vendorName": "IBM", "modelName": "4341-1", "MYCT": 225, "MMIN": 2000, "MMAX": 4000, "CACH": 8, "CHMIN": 3, "CHMAX": 6, "PRP": 40, "ERP": 31 },
    { "vendorName": "IBM", "modelName": "4341-10", "MYCT": 225, "MMIN": 2000, "MMAX": 4000, "CACH": 8, "CHMIN": 3, "CHMAX": 6, "PRP": 34, "ERP": 31 },
    { "vendorName": "IBM", "modelName": "4341-11", "MYCT": 180, "MMIN": 2000, "MMAX": 8000, "CACH": 8, "CHMIN": 1, "CHMAX": 6, "PRP": 50, "ERP": 42 },
    { "vendorName": "IBM", "modelName": "4341-12", "MYCT": 185, "MMIN": 2000, "MMAX": 16000, "CACH": 16, "CHMIN": 1, "CHMAX": 6, "PRP": 76, "ERP": 76 },
    { "vendorName": "IBM", "modelName": "4341-2", "MYCT": 180, "MMIN": 2000, "MMAX": 16000, "CACH": 16, "CHMIN": 1, "CHMAX": 6, "PRP": 66, "ERP": 76 },
    { "vendorName": "IBM", "modelName": "4341-9", "MYCT": 225, "MMIN": 1000, "MMAX": 4000, "CACH": 2, "CHMIN": 3, "CHMAX": 6, "PRP": 24, "ERP": 26 },
    { "vendorName": "IBM", "modelName": "4361-4", "MYCT": 25, "MMIN": 2000, "MMAX": 12000, "CACH": 8, "CHMIN": 1, "CHMAX": 4, "PRP": 49, "ERP": 59 },
    { "vendorName": "IBM", "modelName": "4361-5", "MYCT": 25, "MMIN": 2000, "MMAX": 12000, "CACH": 16, "CHMIN": 3, "CHMAX": 5, "PRP": 66, "ERP": 65 },
    { "vendorName": "IBM", "modelName": "4381-1", "MYCT": 17, "MMIN": 4000, "MMAX": 16000, "CACH": 8, "CHMIN": 6, "CHMAX": 12, "PRP": 100, "ERP": 101 },
    { "vendorName": "IBM", "modelName": "4381-2", "MYCT": 17, "MMIN": 4000, "MMAX": 16000, "CACH": 32, "CHMIN": 6, "CHMAX": 12, "PRP": 133, "ERP": 116 },
    { "vendorName": "IBM", "modelName": "8130-a", "MYCT": 1500, "MMIN": 768, "MMAX": 1000, "CACH": 0, "CHMIN": 0, "CHMAX": 0, "PRP": 12, "ERP": 18 },
    { "vendorName": "IBM", "modelName": "8130-b", "MYCT": 1500, "MMIN": 768, "MMAX": 2000, "CACH": 0, "CHMIN": 0, "CHMAX": 0, "PRP": 18, "ERP": 20 },
    { "vendorName": "IBM", "modelName": "8140", "MYCT": 800, "MMIN": 768, "MMAX": 2000, "CACH": 0, "CHMIN": 0, "CHMAX": 0, "PRP": 20, "ERP": 20 }
]